LICENSE
MANIFEST.in
README.md
requirements.txt
setup.py
pytest_relative_path/__init__.py
pytest_relative_path/plugin.py
pytest_relative_path.egg-info/PKG-INFO
pytest_relative_path.egg-info/SOURCES.txt
pytest_relative_path.egg-info/dependency_links.txt
pytest_relative_path.egg-info/entry_points.txt
pytest_relative_path.egg-info/requires.txt
pytest_relative_path.egg-info/top_level.txt
pytest_relative_path.egg-info/zip-safe
tests/test_pytest_relative_path.py