Metadata-Version: 2.4
Name: pytest-relative-path
Version: 0.1.3
Summary: Handle relative path in pytest options or ini configs
Home-page: https://github.com/hanzhichao/pytest-relative-path
Author: Han Zhichao
Author-email: superhin@126.com
License: MIT license
Keywords: pytest,py.test,relative path,datetime format path
Classifier: Framework :: Pytest
Classifier: Programming Language :: Python
Classifier: Topic :: Software Development :: Testing
Classifier: Programming Language :: Python :: 3.7
License-File: LICENSE
Requires-Dist: pytest
Requires-Dist: pytest-runner
Dynamic: author
Dynamic: author-email
Dynamic: classifier
Dynamic: description
Dynamic: description-content-type
Dynamic: home-page
Dynamic: keywords
Dynamic: license
Dynamic: license-file
Dynamic: requires-dist
Dynamic: summary
